conveyer/__init__.py
conveyer/package.py
conveyer/factories/Factory.py
conveyer/factories/__init__.py
conveyer/metrics/__init__.py
conveyer/metrics/accuracy.py
conveyer/metrics/f1.py
conveyer/metrics/precision.py
conveyer/metrics/r2.py
conveyer/metrics/recall.py
conveyer/models/Model.py
conveyer/models/__init__.py
conveyer/models/classification/ClassificationModel.py
conveyer/models/classification/LogisticRegression.py
conveyer/models/classification/RandomForest.py
conveyer/models/classification/XGBoost.py
conveyer/models/classification/__init__.py
conveyer/models/regression/RandomForest.py
conveyer/models/regression/RegressionModel.py
conveyer/models/regression/XGBoost.py
conveyer/models/regression/__init__.py
conveyer/preprocessing/Parser.py
conveyer/preprocessing/Scaler.py
conveyer/preprocessing/__init__.py
conveyer/readers/__init__.py
conveyer/readers/csv_reader.py
conveyer/types/Task.py
conveyer/types/__init__.py
conveyer-0.1.0.dist-info/METADATA
conveyer-0.1.0.dist-info/RECORD
conveyer-0.1.0.dist-info/WHEEL
conveyer-0.1.0.dist-info/top_level.txt
