Metadata-Version: 2.1
Name: conveyer
Version: 0.1.0
Summary: Automated machine learning library
Home-page: https://github.com/yusugomori/conveyer
Author: Yusuke Sugomori
Author-email: me@yusugomori.com
License: UNKNOWN
Keywords: automated machine learning
Platform: UNKNOWN
Classifier: Development Status :: 3 - Alpha
Classifier: Intended Audience :: Developers
Classifier: Intended Audience :: Education
Classifier: Intended Audience :: Science/Research
Classifier: Programming Language :: Python :: 3
Classifier: Topic :: Scientific/Engineering
Classifier: Topic :: Scientific/Engineering :: Mathematics
Classifier: Topic :: Scientific/Engineering :: Artificial Intelligence
Classifier: Topic :: Software Development
Classifier: Topic :: Software Development :: Libraries
Classifier: Topic :: Software Development :: Libraries :: Python Modules
Requires-Dist: hyperopt (>=0.1)
Requires-Dist: networkx (>=1.11)
Requires-Dist: numpy (>=1.13.3)
Requires-Dist: pandas (>=0.21.0)
Requires-Dist: scikit-learn (>=0.19.1)
Requires-Dist: xgboost (>=0.7)
